levin/__init__.py
levin/bernstein.py
levin/finite_diff.py
levin/hermite.py
levin/common/genbarywts.py
levin/common/utils.py
levin-0.1.0.dist-info/METADATA
levin-0.1.0.dist-info/WHEEL
levin-0.1.0.dist-info/top_level.txt
levin-0.1.0.dist-info/RECORD
