Metadata-Version: 2.1
Name: levin
Version: 0.1.0
Summary: A Python package that implements the Levin methods for highly oscillatory integrals.
Author-email: Jeet Trivedi <jtriv@protonmail.com>
Project-URL: Homepage, https://github.com/jeettrivedi/highly-oscillatory
Project-URL: Bug Tracker, https://github.com/jeettrivedi/highly-oscillatory/issues
Classifier: Programming Language :: Python :: 3
Classifier: License :: OSI Approved :: MIT License
Classifier: Operating System :: OS Independent
Requires-Python: >=3.10
Requires-Dist: coverage>=7.6.4
Requires-Dist: coverage-badge>=1.1.2
Requires-Dist: gitdb>=4.0.11
Requires-Dist: GitPython>=3.1.41
Requires-Dist: iniconfig>=2.0.0
Requires-Dist: mpmath>=1.3.0
Requires-Dist: numpy>=2.1.2
Requires-Dist: packaging>=24.1
Requires-Dist: pluggy>=1.5.0
Requires-Dist: pytest>=8.3.3
Requires-Dist: pytest-cov>=6.0.0
Requires-Dist: scipy>=1.14.1
Requires-Dist: setuptools>=70.0.0
Requires-Dist: smmap>=5.0.1
Requires-Dist: sympy>=1.13.3
